{
  "generator-jhipster": {
    "promptValues": {
      "packageName": "test.org",
      "nativeLanguage": "en"
    },
    "jhipsterVersion": "4.13.3",
    "baseName": "test",
    "packageName": "test.org",
    "packageFolder": "test/org",
    "serverPort": "8081",
    "authenticationType": "jwt",
    "cacheProvider": "hazelcast",
    "enableHibernateCache": false,
    "websocket": false,
    "databaseType": "no",
    "devDatabaseType": "no",
    "prodDatabaseType": "no",
    "searchEngine": false,
    "messageBroker": false,
    "serviceDiscoveryType": "eureka",
    "buildTool": "maven",
    "enableSocialSignIn": false,
    "enableSwaggerCodegen": false,
    "jwtSecretKey": "f4902a6b7fb66348f79263e3b318aea1f2a2037e",
    "enableTranslation": true,
    "applicationType": "microservice",
    "testFrameworks": [],
    "jhiPrefix": "jhi",
    "otherModules": [],
    "nativeLanguage": "en",
    "languages": [
      "en"
    ],
    "clientPackageManager": "yarn",
    "skipClient": true,
    "skipUserManagement": true
  }
}